pyarchinit_mini/__init__.py
pyarchinit_mini/exceptions.py
pyarchinit_mini/api/__init__.py
pyarchinit_mini/api/auth.py
pyarchinit_mini/api/dependencies.py
pyarchinit_mini/api/graphml.py
pyarchinit_mini/api/inventario.py
pyarchinit_mini/api/schemas.py
pyarchinit_mini/api/site.py
pyarchinit_mini/api/us.py
pyarchinit_mini/cli/__init__.py
pyarchinit_mini/cli/export_import_cli.py
pyarchinit_mini/cli/extended_matrix_import.py
pyarchinit_mini/cli/graphml_cli.py
pyarchinit_mini/cli/harris_import.py
pyarchinit_mini/cli/harris_template.py
pyarchinit_mini/cli/migrate.py
pyarchinit_mini/cli/pyarchinit_import_export_cli.py
pyarchinit_mini/cli_interface/__init__.py
pyarchinit_mini/cli_interface/cli_app.py
pyarchinit_mini/config/__init__.py
pyarchinit_mini/config/connection_manager.py
pyarchinit_mini/config/em_node_config_manager.py
pyarchinit_mini/config/em_node_types.yaml
pyarchinit_mini/database/__init__.py
pyarchinit_mini/database/connection.py
pyarchinit_mini/database/database_creator.py
pyarchinit_mini/database/manager.py
pyarchinit_mini/database/migrations.py
pyarchinit_mini/database/postgres_installer.py
pyarchinit_mini/database/schemas.py
pyarchinit_mini/database/migration_scripts/__init__.py
pyarchinit_mini/database/migration_scripts/add_file_path.py
pyarchinit_mini/database/migration_scripts/add_i18n_columns.py
pyarchinit_mini/database/migration_scripts/add_tipo_documento.py
pyarchinit_mini/database/migration_scripts/change_us_area_to_text.py
pyarchinit_mini/database/migration_scripts/change_us_area_to_text_simple.py
pyarchinit_mini/desktop_gui/__init__.py
pyarchinit_mini/desktop_gui/analytics_dialog.py
pyarchinit_mini/desktop_gui/dialogs.py
pyarchinit_mini/desktop_gui/excel_import_dialog.py
pyarchinit_mini/desktop_gui/export_import_dialog.py
pyarchinit_mini/desktop_gui/graphml_export_dialog.py
pyarchinit_mini/desktop_gui/gui_app.py
pyarchinit_mini/desktop_gui/harris_matrix_editor.py
pyarchinit_mini/desktop_gui/i18n.py
pyarchinit_mini/desktop_gui/icons.py
pyarchinit_mini-1.9.38.dist-info/METADATA
pyarchinit_mini-1.9.38.dist-info/WHEEL
pyarchinit_mini-1.9.38.dist-info/entry_points.txt
pyarchinit_mini-1.9.38.dist-info/top_level.txt
pyarchinit_mini-1.9.38.dist-info/RECORD
