Metadata-Version: 2.4
Name: pyarchinit-mini
Version: 1.9.38
Summary: Lightweight archaeological data management system with REST API, Web UI, Desktop GUI, CLI, multi-user authentication, real-time collaboration, analytics dashboard, PyArchInit import/export, Heriverse/ATON export integration, and 3D CRUD viewer
Home-page: https://github.com/enzococca/pyarchinit-mini
Author: PyArchInit Team
Author-email: PyArchInit Team <enzo.ccc@gmail.com>
License: GPL-2.0
Project-URL: Homepage, https://github.com/enzococca/pyarchinit-mini
Project-URL: Documentation, https://github.com/enzococca/pyarchinit-mini/blob/main/README.md
Project-URL: Repository, https://github.com/enzococca/pyarchinit-mini
Project-URL: Bug Tracker, https://github.com/enzococca/pyarchinit-mini/issues
Keywords: archaeology,archaeological data,heritage,cultural heritage,database,api,stratigraphy,excavation,harris matrix,finds inventory
Classifier: Development Status :: 5 - Production/Stable
Classifier: Intended Audience :: Science/Research
Classifier: Topic :: Scientific/Engineering :: GIS
Classifier: Topic :: Database :: Database Engines/Servers
Classifier: License :: OSI Approved :: GNU General Public License v2 (GPLv2)
Classifier: Programming Language :: Python :: 3
Classifier: Programming Language :: Python :: 3.8
Classifier: Programming Language :: Python :: 3.9
Classifier: Programming Language :: Python :: 3.10
Classifier: Programming Language :: Python :: 3.11
Classifier: Programming Language :: Python :: 3.12
Classifier: Programming Language :: Python :: 3.13
Classifier: Programming Language :: Python :: 3.14
Classifier: Operating System :: OS Independent
Classifier: Framework :: FastAPI
Requires-Python: >=3.8,<3.15
Requires-Dist: fastapi>=0.104.0
Requires-Dist: uvicorn[standard]>=0.24.0
Requires-Dist: sqlalchemy>=2.0.0
Requires-Dist: psycopg2-binary>=2.9.0
Requires-Dist: pydantic>=2.0.0
Requires-Dist: pydantic-settings>=2.0.0
Requires-Dist: email-validator>=2.0.0
Requires-Dist: python-multipart>=0.0.6
Requires-Dist: alembic>=1.12.0
Requires-Dist: networkx>=3.0.0
Requires-Dist: reportlab>=4.0.0
Requires-Dist: pillow>=10.0.0
Requires-Dist: s3dgraphy>=0.1.13
Requires-Dist: click>=8.1.0
Requires-Dist: rich>=13.0.0
Requires-Dist: inquirer>=3.0.0
Requires-Dist: flask>=3.0.0
Requires-Dist: flask-wtf>=1.2.0
Requires-Dist: wtforms>=3.1.0
Requires-Dist: jinja2>=3.1.0
Requires-Dist: flask-socketio>=5.3.0
Requires-Dist: python-socketio>=5.10.0
Requires-Dist: flask-babel>=3.1.0
Requires-Dist: babel>=2.12.0
Requires-Dist: passlib>=1.7.4
Requires-Dist: bcrypt<4.1.0,>=4.0.0
Requires-Dist: python-jose[cryptography]>=3.3.0
Requires-Dist: flask-login>=0.6.3
Requires-Dist: matplotlib>=3.7.0
Requires-Dist: graphviz>=0.20.0
Requires-Dist: mcp>=0.1.0
Requires-Dist: weasyprint>=60.0.0
Requires-Dist: python-magic>=0.4.0
Requires-Dist: moviepy>=1.0.0
Requires-Dist: pandas>=2.0.0
Requires-Dist: openpyxl>=3.1.0
Requires-Dist: python-docx>=1.0.0
Requires-Dist: psutil>=5.9.0
Provides-Extra: cli
Provides-Extra: web
Provides-Extra: gui
Provides-Extra: harris
Provides-Extra: pdf
Provides-Extra: media
Provides-Extra: export
Provides-Extra: auth
Provides-Extra: mcp
Provides-Extra: all
Provides-Extra: dev
Requires-Dist: pytest>=7.0.0; extra == "dev"
Requires-Dist: pytest-asyncio>=0.21.0; extra == "dev"
Requires-Dist: pytest-cov>=4.0.0; extra == "dev"
Requires-Dist: httpx>=0.25.0; extra == "dev"
Requires-Dist: black>=23.0.0; extra == "dev"
Requires-Dist: flake8>=6.0.0; extra == "dev"
Requires-Dist: isort>=5.12.0; extra == "dev"
Requires-Dist: mypy>=1.0.0; extra == "dev"
Provides-Extra: docs
Requires-Dist: sphinx>=6.0.0; extra == "docs"
Requires-Dist: sphinx-rtd-theme>=1.2.0; extra == "docs"
Requires-Dist: myst-parser>=1.0.0; extra == "docs"
Dynamic: author
Dynamic: home-page
Dynamic: requires-python
